checklistfabrik/core/__init__.py
checklistfabrik/core/__main__.py
checklistfabrik/core/checklist_data_mapper.py
checklistfabrik/core/checklist_wsgi_app.py
checklistfabrik/core/checklist_wsgi_server.py
checklistfabrik/core/markdown.py
checklistfabrik/core/utils.py
checklistfabrik/core/cli/__init__.py
checklistfabrik/core/cli/base_cli.py
checklistfabrik/core/cli/play.py
checklistfabrik/core/models/__init__.py
checklistfabrik/core/models/checklist.py
checklistfabrik/core/models/page.py
checklistfabrik/core/models/task.py
checklistfabrik/core/templates/__init__.py
checklistfabrik/core/templates/base.html.j2
checklistfabrik/core/templates/checklist.html.j2
checklistfabrik/core/templates/done.html.j2
checklistfabrik/core/templates/navigation_bar.html.j2
checklistfabrik/core/templates/required_indicator.html.j2
checklistfabrik/core/templates/shutdown.html.j2
checklistfabrik/core/templates/steps.html.j2
checklistfabrik/core/templates/assets/css/docs.css
checklistfabrik/core/templates/assets/css/docs.min.css
checklistfabrik/core/templates/assets/css/fontawesome-solid.min.css
checklistfabrik/core/templates/assets/css/fontawesome.min.css
checklistfabrik/core/templates/assets/css/spectre-icons.min.css
checklistfabrik/core/templates/assets/css/spectre.min.css
checklistfabrik/core/templates/assets/css/style.css
checklistfabrik/core/templates/assets/webfonts/fa-solid-900.ttf
checklistfabrik/core/templates/assets/webfonts/fa-solid-900.woff2
checklistfabrik/modules/linuxfabrik/clf/checkbox_input.py
checklistfabrik/modules/linuxfabrik/clf/html.py
checklistfabrik/modules/linuxfabrik/clf/import.py
checklistfabrik/modules/linuxfabrik/clf/markdown.py
checklistfabrik/modules/linuxfabrik/clf/radio_input.py
checklistfabrik/modules/linuxfabrik/clf/select_input.py
checklistfabrik/modules/linuxfabrik/clf/text_input.py
checklistfabrik-1.2.1.dist-info/licenses/LICENSE
checklistfabrik-1.2.1.dist-info/METADATA
checklistfabrik-1.2.1.dist-info/WHEEL
checklistfabrik-1.2.1.dist-info/entry_points.txt
checklistfabrik-1.2.1.dist-info/top_level.txt
checklistfabrik-1.2.1.dist-info/RECORD
