Metadata-Version: 2.4
Name: checklistfabrik
Version: 1.2.1
Summary: ChecklistFabrik is a Python 3 tool to simplify and automate process management using HTML checklists backed by YAML files.
Author-email: "Linuxfabrik GmbH, Zurich, Switzerland" <info@linuxfabrik.ch>
License: This is free and unencumbered software released into the public domain.
Project-URL: Download, https://github.com/linuxfabrik/checklistfabrik/releases/
Project-URL: Homepage, https://github.com/linuxfabrik/checklistfabrik/
Project-URL: Source, https://github.com/linuxfabrik/checklistfabrik/
Project-URL: Tracker, https://github.com/linuxfabrik/checklistfabrik/issues/
Requires-Python: >=3.9
License-File: LICENSE
Requires-Dist: Jinja2~=3.1.6
Requires-Dist: mistune~=3.1.3
Requires-Dist: ruamel.yaml~=0.18.14
Requires-Dist: Werkzeug~=3.1.3
Dynamic: license-file
